pydantic_choices/__init__.py
pydantic_choices/main.py
pydantic_choices-0.1.1.dist-info/LICENSE
pydantic_choices-0.1.1.dist-info/WHEEL
pydantic_choices-0.1.1.dist-info/METADATA
pydantic_choices-0.1.1.dist-info/RECORD
