Metadata-Version: 2.1
Name: pydantic-choices
Version: 0.1.1
Summary: 
Home-page: https://github.com/vinissimus/pydantic-choices
License: MIT
Author: Jordi Masip
Author-email: jordi@masip.cat
Requires-Python: >=3.6,<4.0
Classifier: License :: OSI Approved :: MIT License
Classifier: Programming Language :: Python :: 3
Classifier: Programming Language :: Python :: 3.6
Classifier: Programming Language :: Python :: 3.7
Classifier: Programming Language :: Python :: 3.8
Project-URL: Repository, https://github.com/vinissimus/pydantic-choices
